{
    "filters": {
        "lecturer": "茂木龍太",
        "lecturerKey": "be4c3a1d7652"
    },
    "count": 2,
    "lectures": [
        {
            "lectureCode": "S2230",
            "courseName": "コンピュータグラフィックス論",
            "lecturer": [
                "茂木龍太"
            ],
            "regularOrIntensive": "専門教育科目専門",
            "courseType": "講義科目",
            "courseStart": "2022年度前期",
            "classPeriod": [
                "金3"
            ],
            "targetDepartment": "デザイン学部デザイン学科",
            "targetGrade": [
                "2年",
                "3年",
                "4年"
            ],
            "numberOfCredits": 2,
            "classroom": [
                "３１００１階段教室２"
            ],
            "updateAt": "2022\/03\/25",
            "path": "\/api\/v1\/archive\/2022\/all\/S2230.json"
        },
        {
            "lectureCode": "M301801",
            "courseName": "コンテンツディベロッピング論",
            "lecturer": [
                "茂木龍太",
                "三上浩司"
            ],
            "regularOrIntensive": "専門教育科目コース専門",
            "courseType": "講義科目",
            "courseStart": "2022年度後期",
            "classPeriod": [
                "火2"
            ],
            "targetDepartment": "メディア学部メディア学科",
            "targetGrade": [
                "3年",
                "4年"
            ],
            "numberOfCredits": 2,
            "classroom": [
                "研究棟Ａ４０２"
            ],
            "updateAt": "2022\/02\/02",
            "path": "\/api\/v1\/archive\/2022\/all\/M301801.json"
        }
    ]
}