{
    "filters": {
        "regularOrIntensive": "専門教育科目共通",
        "regularOrIntensiveKey": "7b13cec5830f"
    },
    "count": 40,
    "lectures": [
        {
            "lectureCode": "S1060",
            "courseName": "デジタルスキルA［クラス共通］",
            "lecturer": [
                "田邉雄一",
                "田崎咲絵"
            ],
            "regularOrIntensive": "専門教育科目共通",
            "courseType": "演習科目",
            "courseStart": "2026年度前期",
            "classPeriod": [
                "月1",
                "月2",
                "火1",
                "火2"
            ],
            "targetDepartment": "デザイン学部デザイン学科",
            "targetGrade": [
                "1年",
                "2年",
                "3年",
                "4年"
            ],
            "numberOfCredits": 2,
            "classroom": [
                "３１１１１教室",
                "３１１１２教室",
                "３１１１３教室"
            ],
            "updateAt": "2026\/03\/13",
            "path": "\/api\/v1\/archive\/2026\/all\/S1060.json"
        },
        {
            "lectureCode": "S1061",
            "courseName": "デジタルスキルA［AC1］",
            "lecturer": [
                "樋口泰行",
                "田邉雄一"
            ],
            "regularOrIntensive": "専門教育科目共通",
            "courseType": "演習科目",
            "courseStart": "2026年度前期",
            "classPeriod": [
                "月1",
                "月2"
            ],
            "targetDepartment": "デザイン学部デザイン学科",
            "targetGrade": [
                "1年",
                "2年",
                "3年",
                "4年"
            ],
            "numberOfCredits": 2,
            "classroom": [
                "３１１１１教室"
            ],
            "updateAt": "2026\/03\/23",
            "path": "\/api\/v1\/archive\/2026\/all\/S1061.json"
        },
        {
            "lectureCode": "S1062",
            "courseName": "デジタルスキルA［AC2］",
            "lecturer": [
                "川端亜衣",
                "田邉雄一"
            ],
            "regularOrIntensive": "専門教育科目共通",
            "courseType": "演習科目",
            "courseStart": "2026年度前期",
            "classPeriod": [
                "月1",
                "月2"
            ],
            "targetDepartment": "デザイン学部デザイン学科",
            "targetGrade": [
                "1年",
                "2年",
                "3年",
                "4年"
            ],
            "numberOfCredits": 2,
            "classroom": [
                "３１１１２教室"
            ],
            "updateAt": "2026\/03\/23",
            "path": "\/api\/v1\/archive\/2026\/all\/S1062.json"
        },
        {
            "lectureCode": "S1063",
            "courseName": "デジタルスキルA［AC3］",
            "lecturer": [
                "武藤康恵",
                "田邉雄一"
            ],
            "regularOrIntensive": "専門教育科目共通",
            "courseType": "演習科目",
            "courseStart": "2026年度前期",
            "classPeriod": [
                "月1",
                "月2"
            ],
            "targetDepartment": "デザイン学部デザイン学科",
            "targetGrade": [
                "1年",
                "2年",
                "3年",
                "4年"
            ],
            "numberOfCredits": 2,
            "classroom": [
                "３１１１３教室"
            ],
            "updateAt": "2026\/03\/23",
            "path": "\/api\/v1\/archive\/2026\/all\/S1063.json"
        },
        {
            "lectureCode": "S3030",
            "courseName": "マネジメント",
            "lecturer": [
                "目黒良門",
                "吉村尚人"
            ],
            "regularOrIntensive": "専門教育科目共通",
            "courseType": "講義科目",
            "courseStart": "2026年度前期",
            "classPeriod": [
                "月3"
            ],
            "targetDepartment": "デザイン学部デザイン学科",
            "targetGrade": [
                "3年",
                "4年"
            ],
            "numberOfCredits": 2,
            "classroom": [
                "３１００１階段教室２"
            ],
            "updateAt": "2026\/02\/25",
            "path": "\/api\/v1\/archive\/2026\/all\/S3030.json"
        },
        {
            "lectureCode": "S3020",
            "courseName": "マーケティング論",
            "lecturer": [
                "目黒良門"
            ],
            "regularOrIntensive": "専門教育科目共通",
            "courseType": "講義科目",
            "courseStart": "2026年度前期",
            "classPeriod": [
                "月5"
            ],
            "targetDepartment": "デザイン学部デザイン学科",
            "targetGrade": [
                "3年",
                "4年"
            ],
            "numberOfCredits": 2,
            "classroom": [
                "３１００１階段教室２"
            ],
            "updateAt": "2026\/01\/19",
            "path": "\/api\/v1\/archive\/2026\/all\/S3020.json"
        },
        {
            "lectureCode": "S1080",
            "courseName": "感性演習I（描く・伝える）［Q共通］",
            "lecturer": [
                "深澤健作"
            ],
            "regularOrIntensive": "専門教育科目共通",
            "courseType": "演習科目",
            "courseStart": "2026年度前期",
            "classPeriod": [
                "木3",
                "木4",
                "木5",
                "金3",
                "金4",
                "金5"
            ],
            "targetDepartment": "デザイン学部デザイン学科",
            "targetGrade": [
                "1年",
                "2年",
                "3年",
                "4年"
            ],
            "numberOfCredits": 3,
            "classroom": [
                "３１３０１デザイン演習室１",
                "３１３１５デザイン演習室４"
            ],
            "updateAt": "2026\/01\/14",
            "path": "\/api\/v1\/archive\/2026\/all\/S1080.json"
        },
        {
            "lectureCode": "S1081q",
            "courseName": "感性演習I（描く・伝える）[1Q／K1・K2共通]",
            "lecturer": [
                "深澤健作"
            ],
            "regularOrIntensive": "専門教育科目共通",
            "courseType": "演習科目",
            "courseStart": "2026年度前期",
            "classPeriod": [
                "木3",
                "木4",
                "木5",
                "金3",
                "金4",
                "金5"
            ],
            "targetDepartment": "デザイン学部デザイン学科",
            "targetGrade": [
                "1年",
                "2年",
                "3年",
                "4年"
            ],
            "numberOfCredits": 3,
            "classroom": [
                "３１３０１デザイン演習室１",
                "３１３１５デザイン演習室４"
            ],
            "updateAt": "2026\/03\/23",
            "path": "\/api\/v1\/archive\/2026\/all\/S1081q.json"
        },
        {
            "lectureCode": "S1082q",
            "courseName": "感性演習I（描く・伝える）[2Q／K3・K4共通]",
            "lecturer": [
                "深澤健作"
            ],
            "regularOrIntensive": "専門教育科目共通",
            "courseType": "演習科目",
            "courseStart": "2026年度前期",
            "classPeriod": [
                "木3",
                "木4",
                "木5",
                "金3",
                "金4",
                "金5"
            ],
            "targetDepartment": "デザイン学部デザイン学科",
            "targetGrade": [
                "1年",
                "2年",
                "3年",
                "4年"
            ],
            "numberOfCredits": 3,
            "classroom": [
                "３１３０１デザイン演習室１",
                "３１３１５デザイン演習室４"
            ],
            "updateAt": "2026\/03\/23",
            "path": "\/api\/v1\/archive\/2026\/all\/S1082q.json"
        },
        {
            "lectureCode": "S1100",
            "courseName": "感性演習I（つくる・関係づける）［Q共通］",
            "lecturer": [
                "酒百宏一",
                "高澤恭子"
            ],
            "regularOrIntensive": "専門教育科目共通",
            "courseType": "演習科目",
            "courseStart": "2026年度前期",
            "classPeriod": [
                "木3",
                "木4",
                "木5",
                "金3",
                "金4",
                "金5"
            ],
            "targetDepartment": "デザイン学部デザイン学科",
            "targetGrade": [
                "1年",
                "2年",
                "3年",
                "4年"
            ],
            "numberOfCredits": 3,
            "classroom": [
                "３１３１１デザイン演習室２",
                "３１３１３デザイン演習室３"
            ],
            "updateAt": "2026\/01\/18",
            "path": "\/api\/v1\/archive\/2026\/all\/S1100.json"
        },
        {
            "lectureCode": "S1101q",
            "courseName": "感性演習I（つくる・関係づける）[1Q／K3・K4共通]",
            "lecturer": [
                "酒百宏一",
                "高澤恭子"
            ],
            "regularOrIntensive": "専門教育科目共通",
            "courseType": "演習科目",
            "courseStart": "2026年度前期",
            "classPeriod": [
                "木3",
                "木4",
                "木5",
                "金3",
                "金4",
                "金5"
            ],
            "targetDepartment": "デザイン学部デザイン学科",
            "targetGrade": [
                "1年",
                "2年",
                "3年",
                "4年"
            ],
            "numberOfCredits": 3,
            "classroom": [
                "３１３１１デザイン演習室２",
                "３１３１３デザイン演習室３"
            ],
            "updateAt": "2026\/03\/23",
            "path": "\/api\/v1\/archive\/2026\/all\/S1101q.json"
        },
        {
            "lectureCode": "S1102q",
            "courseName": "感性演習I（つくる・関係づける）[2Q／K1・K2共通]",
            "lecturer": [
                "酒百宏一",
                "高澤恭子"
            ],
            "regularOrIntensive": "専門教育科目共通",
            "courseType": "演習科目",
            "courseStart": "2026年度前期",
            "classPeriod": [
                "木3",
                "木4",
                "木5",
                "金3",
                "金4",
                "金5"
            ],
            "targetDepartment": "デザイン学部デザイン学科",
            "targetGrade": [
                "1年",
                "2年",
                "3年",
                "4年"
            ],
            "numberOfCredits": 3,
            "classroom": [
                "３１３１１デザイン演習室２",
                "３１３１３デザイン演習室３"
            ],
            "updateAt": "2026\/03\/23",
            "path": "\/api\/v1\/archive\/2026\/all\/S1102q.json"
        },
        {
            "lectureCode": "S2030",
            "courseName": "企画と展示",
            "lecturer": [
                "暮沢剛巳"
            ],
            "regularOrIntensive": "専門教育科目共通",
            "courseType": "講義科目",
            "courseStart": "2026年度前期",
            "classPeriod": [
                "木3"
            ],
            "targetDepartment": "デザイン学部デザイン学科",
            "targetGrade": [
                "2年",
                "3年",
                "4年"
            ],
            "numberOfCredits": 2,
            "classroom": [
                "３Ｂ１１０大講義室（地下ホール）"
            ],
            "updateAt": "2026\/02\/22",
            "path": "\/api\/v1\/archive\/2026\/all\/S2030.json"
        },
        {
            "lectureCode": "S1050",
            "courseName": "立体表現の基礎",
            "lecturer": [
                "酒井正",
                "高澤恭子"
            ],
            "regularOrIntensive": "専門教育科目共通",
            "courseType": "講義科目",
            "courseStart": "2026年度前期",
            "classPeriod": [
                "水1"
            ],
            "targetDepartment": "デザイン学部デザイン学科",
            "targetGrade": [
                "1年",
                "2年",
                "3年",
                "4年"
            ],
            "numberOfCredits": 2,
            "classroom": [
                "３Ｂ１１０大講義室（地下ホール）"
            ],
            "updateAt": "2026\/01\/17",
            "path": "\/api\/v1\/archive\/2026\/all\/S1050.json"
        },
        {
            "lectureCode": "S1064",
            "courseName": "デジタルスキルA［BC1］",
            "lecturer": [
                "古谷峰子",
                "田邉雄一"
            ],
            "regularOrIntensive": "専門教育科目共通",
            "courseType": "演習科目",
            "courseStart": "2026年度前期",
            "classPeriod": [
                "火1",
                "火2"
            ],
            "targetDepartment": "デザイン学部デザイン学科",
            "targetGrade": [
                "1年",
                "2年",
                "3年",
                "4年"
            ],
            "numberOfCredits": 2,
            "classroom": [
                "３１１１１教室"
            ],
            "updateAt": "2026\/03\/23",
            "path": "\/api\/v1\/archive\/2026\/all\/S1064.json"
        },
        {
            "lectureCode": "S1065",
            "courseName": "デジタルスキルA［BC2］",
            "lecturer": [
                "石井英雄",
                "田邉雄一"
            ],
            "regularOrIntensive": "専門教育科目共通",
            "courseType": "演習科目",
            "courseStart": "2026年度前期",
            "classPeriod": [
                "火1",
                "火2"
            ],
            "targetDepartment": "デザイン学部デザイン学科",
            "targetGrade": [
                "1年",
                "2年",
                "3年",
                "4年"
            ],
            "numberOfCredits": 2,
            "classroom": [
                "３１１１２教室"
            ],
            "updateAt": "2026\/03\/23",
            "path": "\/api\/v1\/archive\/2026\/all\/S1065.json"
        },
        {
            "lectureCode": "S1066",
            "courseName": "デジタルスキルA［BC3］",
            "lecturer": [
                "尾花曉",
                "田邉雄一"
            ],
            "regularOrIntensive": "専門教育科目共通",
            "courseType": "演習科目",
            "courseStart": "2026年度前期",
            "classPeriod": [
                "火1",
                "火2"
            ],
            "targetDepartment": "デザイン学部デザイン学科",
            "targetGrade": [
                "1年",
                "2年",
                "3年",
                "4年"
            ],
            "numberOfCredits": 2,
            "classroom": [
                "３１１１３教室"
            ],
            "updateAt": "2026\/03\/23",
            "path": "\/api\/v1\/archive\/2026\/all\/S1066.json"
        },
        {
            "lectureCode": "S1040",
            "courseName": "平面表現の基礎",
            "lecturer": [
                "深澤健作"
            ],
            "regularOrIntensive": "専門教育科目共通",
            "courseType": "講義科目",
            "courseStart": "2026年度前期",
            "classPeriod": [
                "火3"
            ],
            "targetDepartment": "デザイン学部デザイン学科",
            "targetGrade": [
                "1年",
                "2年",
                "3年",
                "4年"
            ],
            "numberOfCredits": 2,
            "classroom": [
                "３１００１階段教室２"
            ],
            "updateAt": "2026\/01\/14",
            "path": "\/api\/v1\/archive\/2026\/all\/S1040.json"
        },
        {
            "lectureCode": "S3010",
            "courseName": "知的財産論",
            "lecturer": [
                "町田侑太",
                "暮沢剛巳"
            ],
            "regularOrIntensive": "専門教育科目共通",
            "courseType": "講義科目",
            "courseStart": "2026年度前期",
            "classPeriod": [
                "火5"
            ],
            "targetDepartment": "デザイン学部デザイン学科",
            "targetGrade": [
                "3年",
                "4年"
            ],
            "numberOfCredits": 2,
            "classroom": [
                "３Ｂ１１０大講義室（地下ホール）"
            ],
            "updateAt": "2026\/03\/07",
            "path": "\/api\/v1\/archive\/2026\/all\/S3010.json"
        },
        {
            "lectureCode": "S1010",
            "courseName": "デザイン概説I",
            "lecturer": [
                "酒百宏一"
            ],
            "regularOrIntensive": "専門教育科目共通",
            "courseType": "講義科目",
            "courseStart": "2026年度前期",
            "classPeriod": [
                "金2"
            ],
            "targetDepartment": "デザイン学部デザイン学科",
            "targetGrade": [
                "1年",
                "2年",
                "3年",
                "4年"
            ],
            "numberOfCredits": 2,
            "classroom": [
                "３Ｂ１１０大講義室（地下ホール）"
            ],
            "updateAt": "2026\/01\/16",
            "path": "\/api\/v1\/archive\/2026\/all\/S1010.json"
        },
        {
            "lectureCode": "S2010",
            "courseName": "社会と美術",
            "lecturer": [
                "暮沢剛巳"
            ],
            "regularOrIntensive": "専門教育科目共通",
            "courseType": "講義科目",
            "courseStart": "2026年度前期",
            "classPeriod": [
                "金3"
            ],
            "targetDepartment": "デザイン学部デザイン学科",
            "targetGrade": [
                "2年",
                "3年",
                "4年"
            ],
            "numberOfCredits": 2,
            "classroom": [
                "３１００１階段教室２"
            ],
            "updateAt": "2026\/01\/16",
            "path": "\/api\/v1\/archive\/2026\/all\/S2010.json"
        },
        {
            "lectureCode": "S2050",
            "courseName": "プレゼンテーションの基礎",
            "lecturer": [
                "田邉雄一"
            ],
            "regularOrIntensive": "専門教育科目共通",
            "courseType": "講義科目",
            "courseStart": "2026年度後期",
            "classPeriod": [
                "月1"
            ],
            "targetDepartment": "デザイン学部デザイン学科",
            "targetGrade": [
                "2年",
                "3年",
                "4年"
            ],
            "numberOfCredits": 2,
            "classroom": [
                "３１００１階段教室２"
            ],
            "updateAt": "2026\/03\/07",
            "path": "\/api\/v1\/archive\/2026\/all\/S2050.json"
        },
        {
            "lectureCode": "S1070",
            "courseName": "デジタルスキルB［クラス共通］",
            "lecturer": [
                "田邉雄一",
                "田崎咲絵"
            ],
            "regularOrIntensive": "専門教育科目共通",
            "courseType": "演習科目",
            "courseStart": "2026年度後期",
            "classPeriod": [
                "月3",
                "月4",
                "火3",
                "火4"
            ],
            "targetDepartment": "デザイン学部デザイン学科",
            "targetGrade": [
                "1年",
                "2年",
                "3年",
                "4年"
            ],
            "numberOfCredits": 2,
            "classroom": [
                "３１１１１教室",
                "３１１１２教室",
                "３１１１３教室"
            ],
            "updateAt": "2026\/06\/19",
            "path": "\/api\/v1\/archive\/2026\/all\/S1070.json"
        },
        {
            "lectureCode": "S1074",
            "courseName": "デジタルスキルB［BC1］",
            "lecturer": [
                "樋口泰行",
                "田崎咲絵"
            ],
            "regularOrIntensive": "専門教育科目共通",
            "courseType": "演習科目",
            "courseStart": "2026年度後期",
            "classPeriod": [
                "月3",
                "月4"
            ],
            "targetDepartment": "デザイン学部デザイン学科",
            "targetGrade": [
                "1年",
                "2年",
                "3年",
                "4年"
            ],
            "numberOfCredits": 2,
            "classroom": [
                "３１１１１教室"
            ],
            "updateAt": "2026\/06\/19",
            "path": "\/api\/v1\/archive\/2026\/all\/S1074.json"
        },
        {
            "lectureCode": "S1075",
            "courseName": "デジタルスキルB［BC2］",
            "lecturer": [
                "川端亜衣",
                "田崎咲絵"
            ],
            "regularOrIntensive": "専門教育科目共通",
            "courseType": "演習科目",
            "courseStart": "2026年度後期",
            "classPeriod": [
                "月3",
                "月4"
            ],
            "targetDepartment": "デザイン学部デザイン学科",
            "targetGrade": [
                "1年",
                "2年",
                "3年",
                "4年"
            ],
            "numberOfCredits": 2,
            "classroom": [
                "３１１１２教室"
            ],
            "updateAt": "2026\/06\/19",
            "path": "\/api\/v1\/archive\/2026\/all\/S1075.json"
        },
        {
            "lectureCode": "S1076",
            "courseName": "デジタルスキルB［BC3］",
            "lecturer": [
                "田島知華",
                "田崎咲絵"
            ],
            "regularOrIntensive": "専門教育科目共通",
            "courseType": "演習科目",
            "courseStart": "2026年度後期",
            "classPeriod": [
                "月3",
                "月4"
            ],
            "targetDepartment": "デザイン学部デザイン学科",
            "targetGrade": [
                "1年",
                "2年",
                "3年",
                "4年"
            ],
            "numberOfCredits": 2,
            "classroom": [
                "３１１１３教室"
            ],
            "updateAt": "2026\/06\/19",
            "path": "\/api\/v1\/archive\/2026\/all\/S1076.json"
        },
        {
            "lectureCode": "S3040",
            "courseName": "経営・経済論",
            "lecturer": [
                "辻井康一",
                "赤津慎二"
            ],
            "regularOrIntensive": "専門教育科目共通",
            "courseType": "講義科目",
            "courseStart": "2026年度後期",
            "classPeriod": [
                "月3"
            ],
            "targetDepartment": "デザイン学部デザイン学科",
            "targetGrade": [
                "3年",
                "4年"
            ],
            "numberOfCredits": 2,
            "classroom": [
                "３０２１２教室"
            ],
            "updateAt": "2026\/03\/10",
            "path": "\/api\/v1\/archive\/2026\/all\/S3040.json"
        },
        {
            "lectureCode": "S1090",
            "courseName": "感性演習II（描く・伝える）［Q共通］",
            "lecturer": [
                "深澤健作"
            ],
            "regularOrIntensive": "専門教育科目共通",
            "courseType": "演習科目",
            "courseStart": "2026年度後期",
            "classPeriod": [
                "木3",
                "木4",
                "木5",
                "金3",
                "金4",
                "金5"
            ],
            "targetDepartment": "デザイン学部デザイン学科",
            "targetGrade": [
                "1年",
                "2年",
                "3年",
                "4年"
            ],
            "numberOfCredits": 3,
            "classroom": [
                "３１３０１デザイン演習室１",
                "３１３１５デザイン演習室４"
            ],
            "updateAt": "2026\/02\/22",
            "path": "\/api\/v1\/archive\/2026\/all\/S1090.json"
        },
        {
            "lectureCode": "S1093q",
            "courseName": "感性演習II（描く・伝える）[3Q／K1・K2共通]",
            "lecturer": [
                "深澤健作"
            ],
            "regularOrIntensive": "専門教育科目共通",
            "courseType": "演習科目",
            "courseStart": "2026年度後期",
            "classPeriod": [
                "木3",
                "木4",
                "木5",
                "金3",
                "金4",
                "金5"
            ],
            "targetDepartment": "デザイン学部デザイン学科",
            "targetGrade": [
                "1年",
                "2年",
                "3年",
                "4年"
            ],
            "numberOfCredits": 3,
            "classroom": [
                "３１３０１デザイン演習室１",
                "３１３１５デザイン演習室４"
            ],
            "updateAt": "2026\/04\/07",
            "path": "\/api\/v1\/archive\/2026\/all\/S1093q.json"
        },
        {
            "lectureCode": "S1094q",
            "courseName": "感性演習II（描く・伝える）[4Q／K3・K4共通]",
            "lecturer": [
                "深澤健作"
            ],
            "regularOrIntensive": "専門教育科目共通",
            "courseType": "演習科目",
            "courseStart": "2026年度後期",
            "classPeriod": [
                "木3",
                "木4",
                "木5",
                "金3",
                "金4",
                "金5"
            ],
            "targetDepartment": "デザイン学部デザイン学科",
            "targetGrade": [
                "1年",
                "2年",
                "3年",
                "4年"
            ],
            "numberOfCredits": 3,
            "classroom": [
                "３１３０１デザイン演習室１",
                "３１３１５デザイン演習室４"
            ],
            "updateAt": "2026\/04\/07",
            "path": "\/api\/v1\/archive\/2026\/all\/S1094q.json"
        },
        {
            "lectureCode": "S1110",
            "courseName": "感性演習II（つくる・関係づける）［Q共通］",
            "lecturer": [
                "御幸朋寿",
                "高澤恭子"
            ],
            "regularOrIntensive": "専門教育科目共通",
            "courseType": "演習科目",
            "courseStart": "2026年度後期",
            "classPeriod": [
                "木3",
                "木4",
                "木5",
                "金3",
                "金4",
                "金5"
            ],
            "targetDepartment": "デザイン学部デザイン学科",
            "targetGrade": [
                "1年",
                "2年",
                "3年",
                "4年"
            ],
            "numberOfCredits": 3,
            "classroom": [
                "３１３１１デザイン演習室２",
                "３１３１３デザイン演習室３"
            ],
            "updateAt": "2026\/01\/18",
            "path": "\/api\/v1\/archive\/2026\/all\/S1110.json"
        },
        {
            "lectureCode": "S1113q",
            "courseName": "感性演習II（つくる・関係づける）[3Q／K3・K4共通]",
            "lecturer": [
                "御幸朋寿",
                "高澤恭子"
            ],
            "regularOrIntensive": "専門教育科目共通",
            "courseType": "演習科目",
            "courseStart": "2026年度後期",
            "classPeriod": [
                "木3",
                "木4",
                "木5",
                "金3",
                "金4",
                "金5"
            ],
            "targetDepartment": "デザイン学部デザイン学科",
            "targetGrade": [
                "1年",
                "2年",
                "3年",
                "4年"
            ],
            "numberOfCredits": 3,
            "classroom": [
                "３１３１１デザイン演習室２",
                "３１３１３デザイン演習室３"
            ],
            "updateAt": "2026\/04\/07",
            "path": "\/api\/v1\/archive\/2026\/all\/S1113q.json"
        },
        {
            "lectureCode": "S1114q",
            "courseName": "感性演習II（つくる・関係づける）[4Q／K1・K2共通]",
            "lecturer": [
                "御幸朋寿",
                "高澤恭子"
            ],
            "regularOrIntensive": "専門教育科目共通",
            "courseType": "演習科目",
            "courseStart": "2026年度後期",
            "classPeriod": [
                "木3",
                "木4",
                "木5",
                "金3",
                "金4",
                "金5"
            ],
            "targetDepartment": "デザイン学部デザイン学科",
            "targetGrade": [
                "1年",
                "2年",
                "3年",
                "4年"
            ],
            "numberOfCredits": 3,
            "classroom": [
                "３１３１１デザイン演習室２",
                "３１３１３デザイン演習室３"
            ],
            "updateAt": "2026\/04\/07",
            "path": "\/api\/v1\/archive\/2026\/all\/S1114q.json"
        },
        {
            "lectureCode": "S2020",
            "courseName": "デザイン史",
            "lecturer": [
                "暮沢剛巳"
            ],
            "regularOrIntensive": "専門教育科目共通",
            "courseType": "講義科目",
            "courseStart": "2026年度後期",
            "classPeriod": [
                "木3"
            ],
            "targetDepartment": "デザイン学部デザイン学科",
            "targetGrade": [
                "2年",
                "3年",
                "4年"
            ],
            "numberOfCredits": 2,
            "classroom": [
                "３Ｂ１１０大講義室（地下ホール）"
            ],
            "updateAt": "2026\/01\/16",
            "path": "\/api\/v1\/archive\/2026\/all\/S2020.json"
        },
        {
            "lectureCode": "S1030",
            "courseName": "色彩概論",
            "lecturer": [
                "早瀬交宣"
            ],
            "regularOrIntensive": "専門教育科目共通",
            "courseType": "講義科目",
            "courseStart": "2026年度後期",
            "classPeriod": [
                "火1"
            ],
            "targetDepartment": "デザイン学部デザイン学科",
            "targetGrade": [
                "1年",
                "2年",
                "3年",
                "4年"
            ],
            "numberOfCredits": 2,
            "classroom": [
                "３Ｂ１１０大講義室（地下ホール）"
            ],
            "updateAt": "2026\/03\/07",
            "path": "\/api\/v1\/archive\/2026\/all\/S1030.json"
        },
        {
            "lectureCode": "S2040",
            "courseName": "サブカルチャー論",
            "lecturer": [
                "暮沢剛巳"
            ],
            "regularOrIntensive": "専門教育科目共通",
            "courseType": "講義科目",
            "courseStart": "2026年度後期",
            "classPeriod": [
                "火2"
            ],
            "targetDepartment": "デザイン学部デザイン学科",
            "targetGrade": [
                "2年",
                "3年",
                "4年"
            ],
            "numberOfCredits": 2,
            "classroom": [
                "３１００１階段教室２"
            ],
            "updateAt": "2026\/01\/16",
            "path": "\/api\/v1\/archive\/2026\/all\/S2040.json"
        },
        {
            "lectureCode": "S1071",
            "courseName": "デジタルスキルB［AC1］",
            "lecturer": [
                "古谷峰子",
                "田崎咲絵"
            ],
            "regularOrIntensive": "専門教育科目共通",
            "courseType": "演習科目",
            "courseStart": "2026年度後期",
            "classPeriod": [
                "火3",
                "火4"
            ],
            "targetDepartment": "デザイン学部デザイン学科",
            "targetGrade": [
                "1年",
                "2年",
                "3年",
                "4年"
            ],
            "numberOfCredits": 2,
            "classroom": [
                "３１１１１教室"
            ],
            "updateAt": "2026\/06\/19",
            "path": "\/api\/v1\/archive\/2026\/all\/S1071.json"
        },
        {
            "lectureCode": "S1072",
            "courseName": "デジタルスキルB［AC2］",
            "lecturer": [
                "小藤貴之",
                "田崎咲絵"
            ],
            "regularOrIntensive": "専門教育科目共通",
            "courseType": "演習科目",
            "courseStart": "2026年度後期",
            "classPeriod": [
                "火3",
                "火4"
            ],
            "targetDepartment": "デザイン学部デザイン学科",
            "targetGrade": [
                "1年",
                "2年",
                "3年",
                "4年"
            ],
            "numberOfCredits": 2,
            "classroom": [
                "３１１１２教室"
            ],
            "updateAt": "2026\/06\/19",
            "path": "\/api\/v1\/archive\/2026\/all\/S1072.json"
        },
        {
            "lectureCode": "S1073",
            "courseName": "デジタルスキルB［AC3］",
            "lecturer": [
                "尾花曉",
                "田崎咲絵"
            ],
            "regularOrIntensive": "専門教育科目共通",
            "courseType": "演習科目",
            "courseStart": "2026年度後期",
            "classPeriod": [
                "火3",
                "火4"
            ],
            "targetDepartment": "デザイン学部デザイン学科",
            "targetGrade": [
                "1年",
                "2年",
                "3年",
                "4年"
            ],
            "numberOfCredits": 2,
            "classroom": [
                "３１１１３教室"
            ],
            "updateAt": "2026\/06\/19",
            "path": "\/api\/v1\/archive\/2026\/all\/S1073.json"
        },
        {
            "lectureCode": "S1020",
            "courseName": "デザイン概説II",
            "lecturer": [
                "酒百宏一"
            ],
            "regularOrIntensive": "専門教育科目共通",
            "courseType": "講義科目",
            "courseStart": "2026年度後期",
            "classPeriod": [
                "金2"
            ],
            "targetDepartment": "デザイン学部デザイン学科",
            "targetGrade": [
                "1年",
                "2年",
                "3年",
                "4年"
            ],
            "numberOfCredits": 2,
            "classroom": [
                "３Ｂ１１０大講義室（地下ホール）"
            ],
            "updateAt": "2026\/01\/16",
            "path": "\/api\/v1\/archive\/2026\/all\/S1020.json"
        }
    ]
}