{
    "lectureCode": "T2500",
    "courseName": "応用コンピュータI",
    "lecturer": [
        "高橋潔"
    ],
    "regularOrIntensive": "基礎教育科目コンピュータ",
    "courseType": "講義科目",
    "courseStart": "2021年度前期",
    "classPeriod": [
        "月1"
    ],
    "targetDepartment": "",
    "targetGrade": [
        "2年",
        "3年",
        "4年"
    ],
    "numberOfCredits": 2,
    "classroom": [
        "３０２０２教室"
    ],
    "courceDetails": {
        "courseOverview": "PCやスマフォでアプリを利用する機会が増えています。そのアプリを動作させている仕組みをプログラミングから理解することを目的としています。授業ではプログラミング言語Python3を利用します。Python3とタートルグラフィックスを利用し、プログラミングを学修します。＊タートルグラフィックスとは、コンピュータ画面上に仮想的な亀に指示を出し、移動した軌跡を図として表示する仕組みです。亀への指示をプログラミングできるため、プログラムの動作を視覚的に確かめることが容易です。",
        "outcomesMeasuredBy": "1.プログラムのアルゴリズムを説明できる。（論理的な思考能力）2.タートルグラフックスのプログラムを説明できる。（論理的な思考能力）3.基本的なプログラムを作成できる。（実学に基づく専門能力）",
        "learningOutcomes": "",
        "teachingMethod": "この授業はオンデマンドで行います。教材を利用し、学修して下さい。Windows10を使用します。",
        "notices": "「コンピュータ概論１」、「コンピュータ概論２」を修得していることが望ましい。",
        "preparatoryStudy": "この授業はオンデマンドで行います。Moodleの資料と課題を確認してください。",
        "gradingGuidelines": "授業への取り組みと到達演習（60％）、全体のまとめと理解度チェック（40％）により評価する。",
        "textbook": "特に指定はありません。",
        "referenceMaterials": "みんなのPython第3版（SBCreative)、柴田淳",
        "courseSchedule": "第1回:パソコンの操作（１）講義の概要説明とWindows10の環境設定第2回:パソコンの操作（２）python3のインストール第3回:プログラミングの基礎（１）タートルグラフィックスとは第4回:プログラミングの基礎（２）対話実行モードでのタートルグラフィックスを実行する第5回:プログラミングの基礎（３）開発環境でのタートルグラフィックスを実行する第6回:プログラミングの基礎（４）タートルグラフィックスで図形を描く第7回:まとめと到達演習第8回:プログラミング（１）変数について第9回:プログラミング（２）データ型について第10回:プログラミング（３）制御文について第11回:プログラミング（４）関数について第12回:プログラミング（５）クラスについて第13回:まとめと到達演習第14回:全体のまとめと理解度チェック（１）第15回:全体のまとめと理解度チェック（２）",
        "courseDataUpdatedAt": "2021\/03\/15"
    },
    "updateAt": "2021\/03\/15"
}