{
    "filters": {
        "lecturer": "森川美幸",
        "lecturerKey": "57cfd6562794"
    },
    "count": 11,
    "lectures": [
        {
            "lectureCode": "M400131",
            "courseName": "卒業研究Ｉ",
            "lecturer": [
                "森川美幸"
            ],
            "regularOrIntensive": "専門教育科目総合・演習",
            "courseType": "演習科目",
            "courseStart": "2020年度前期",
            "classPeriod": [
                "他"
            ],
            "targetDepartment": "メディア学部メディア学科",
            "targetGrade": [
                "4年"
            ],
            "numberOfCredits": 4,
            "classroom": [],
            "updateAt": "2020\/02\/25",
            "path": "\/api\/v1\/archive\/2020\/all\/M400131.json"
        },
        {
            "lectureCode": "11050M33",
            "courseName": "フレッシャーズゼミＩ",
            "lecturer": [
                "森川美幸"
            ],
            "regularOrIntensive": "教養教育科目人間形成",
            "courseType": "演習科目",
            "courseStart": "2020年度前期",
            "classPeriod": [
                "月3"
            ],
            "targetDepartment": "メディア学部メディア学科",
            "targetGrade": [
                "1年",
                "2年",
                "3年",
                "4年"
            ],
            "numberOfCredits": 1,
            "classroom": [],
            "updateAt": "2020\/02\/25",
            "path": "\/api\/v1\/archive\/2020\/all\/11050M33.json"
        },
        {
            "lectureCode": "M3001S4",
            "courseName": "メディア専門演習II（映画プロジェクト開発）",
            "lecturer": [
                "森川美幸"
            ],
            "regularOrIntensive": "専門教育科目総合・演習",
            "courseType": "演習科目",
            "courseStart": "2020年度前期",
            "classPeriod": [
                "木1",
                "木2"
            ],
            "targetDepartment": "メディア学部メディア学科",
            "targetGrade": [
                "3年",
                "4年"
            ],
            "numberOfCredits": 2,
            "classroom": [],
            "updateAt": "2019\/12\/25",
            "path": "\/api\/v1\/archive\/2020\/all\/M3001S4.json"
        },
        {
            "lectureCode": "G1339001",
            "courseName": "メディアビジネス特論",
            "lecturer": [
                "森川美幸"
            ],
            "regularOrIntensive": "専門科目メディアサイエンス専攻",
            "courseType": "講義科目",
            "courseStart": "2020年度前期",
            "classPeriod": [
                "水1"
            ],
            "targetDepartment": "バイオ・情報メディア研究科博士前期課程メディアサイエンス専攻",
            "targetGrade": [
                "1年",
                "2年"
            ],
            "numberOfCredits": 1,
            "classroom": [
                "片柳研究所Ｅ２０３"
            ],
            "updateAt": "2020\/03\/02",
            "path": "\/api\/v1\/archive\/2020\/all\/G1339001.json"
        },
        {
            "lectureCode": "M101101",
            "courseName": "メディア文化と社会",
            "lecturer": [
                "榎本美香",
                "森川美幸"
            ],
            "regularOrIntensive": "専門基礎教育科目メディア基礎",
            "courseType": "講義科目",
            "courseStart": "2020年度前期",
            "classPeriod": [
                "水2"
            ],
            "targetDepartment": "",
            "targetGrade": [
                "1年",
                "2年",
                "3年",
                "4年"
            ],
            "numberOfCredits": 2,
            "classroom": [
                "片柳研究所Ｅ４０２"
            ],
            "updateAt": "2020\/03\/23",
            "path": "\/api\/v1\/archive\/2020\/all\/M101101.json"
        },
        {
            "lectureCode": "M200501",
            "courseName": "デジタルジャーナリズム入門",
            "lecturer": [
                "森川美幸"
            ],
            "regularOrIntensive": "専門基礎教育科目メディア基礎",
            "courseType": "講義科目",
            "courseStart": "2020年度前期",
            "classPeriod": [
                "水3"
            ],
            "targetDepartment": "メディア学部メディア学科",
            "targetGrade": [
                "2年",
                "3年",
                "4年"
            ],
            "numberOfCredits": 2,
            "classroom": [
                "片柳研究所Ｅ４０２"
            ],
            "updateAt": "2019\/12\/25",
            "path": "\/api\/v1\/archive\/2020\/all\/M200501.json"
        },
        {
            "lectureCode": "M400228",
            "courseName": "卒業研究II",
            "lecturer": [
                "森川美幸"
            ],
            "regularOrIntensive": "専門教育科目総合・演習",
            "courseType": "演習科目",
            "courseStart": "2020年度後期",
            "classPeriod": [
                "他"
            ],
            "targetDepartment": "メディア学部メディア学科",
            "targetGrade": [
                "4年"
            ],
            "numberOfCredits": 4,
            "classroom": [],
            "updateAt": "2020\/02\/25",
            "path": "\/api\/v1\/archive\/2020\/all\/M400228.json"
        },
        {
            "lectureCode": "M2011T6",
            "courseName": "メディア専門演習I（映画プロジェクト開発）",
            "lecturer": [
                "森川美幸"
            ],
            "regularOrIntensive": "専門教育科目総合・演習",
            "courseType": "演習科目",
            "courseStart": "2020年度後期",
            "classPeriod": [
                "木1",
                "木2"
            ],
            "targetDepartment": "メディア学部メディア学科",
            "targetGrade": [
                "2年",
                "3年",
                "4年"
            ],
            "numberOfCredits": 2,
            "classroom": [],
            "updateAt": "2020\/06\/12",
            "path": "\/api\/v1\/archive\/2020\/all\/M2011T6.json"
        },
        {
            "lectureCode": "11055M43",
            "courseName": "キャリアデザインIV",
            "lecturer": [
                "森川美幸"
            ],
            "regularOrIntensive": "教養教育科目人間形成",
            "courseType": "演習科目",
            "courseStart": "2020年度後期",
            "classPeriod": [
                "火4"
            ],
            "targetDepartment": "メディア学部メディア学科",
            "targetGrade": [
                "3年",
                "4年"
            ],
            "numberOfCredits": 1,
            "classroom": [],
            "updateAt": "2020\/02\/25",
            "path": "\/api\/v1\/archive\/2020\/all\/11055M43.json"
        },
        {
            "lectureCode": "M300232",
            "courseName": "創成課題",
            "lecturer": [
                "森川美幸"
            ],
            "regularOrIntensive": "専門教育科目総合・演習",
            "courseType": "演習科目",
            "courseStart": "2020年度後期",
            "classPeriod": [
                "金3"
            ],
            "targetDepartment": "メディア学部メディア学科",
            "targetGrade": [
                "3年",
                "4年"
            ],
            "numberOfCredits": 1,
            "classroom": [],
            "updateAt": "2020\/02\/25",
            "path": "\/api\/v1\/archive\/2020\/all\/M300232.json"
        },
        {
            "lectureCode": "11051M34",
            "courseName": "フレッシャーズゼミII",
            "lecturer": [
                "森川美幸"
            ],
            "regularOrIntensive": "教養教育科目人間形成",
            "courseType": "演習科目",
            "courseStart": "2020年度後期",
            "classPeriod": [
                "金4"
            ],
            "targetDepartment": "メディア学部メディア学科",
            "targetGrade": [
                "1年",
                "2年",
                "3年",
                "4年"
            ],
            "numberOfCredits": 1,
            "classroom": [
                "片柳研究所Ｅ３０２"
            ],
            "updateAt": "2021\/04\/26",
            "path": "\/api\/v1\/archive\/2020\/all\/11051M34.json"
        }
    ]
}