{
    "lectureCode": "G1324001",
    "courseName": "音声インターフェース特論",
    "lecturer": [
        "越智景子"
    ],
    "regularOrIntensive": "専門科目メディアサイエンス専攻",
    "courseType": "講義科目",
    "courseStart": "2020年度後期",
    "classPeriod": [
        "月4"
    ],
    "targetDepartment": "バイオ・情報メディア研究科博士前期課程メディアサイエンス専攻",
    "targetGrade": [
        "1年",
        "2年"
    ],
    "numberOfCredits": 1,
    "classroom": [
        "片柳研究所Ｅ２０３"
    ],
    "courceDetails": {
        "courseOverview": "近年、音声を用いたユーザーインターフェースの普及が進んでいる。本講義では音声インターフェースについて、その要素技術である音声信号処理の学習を通じて理解を深める。前半には音声インターフェースに用いられている要素技術について学習し、後半に音声インターフェースの研究事例を紹介する。回によってはフリーウェアを使った音声信号処理の演習や音声インターフェースに関わる論文調査を行う場合がある。",
        "outcomesMeasuredBy": "音声インターフェース技術の理解と用いられている音声信号処理技術の知識の習得。",
        "learningOutcomes": "",
        "teachingMethod": "音声インターフェースに関わる国際論文誌、国際会議論文等の紹介と解説、および各自の文献調査と輪講を行う。音声信号処理のフリーウェアのツールによる演習を行う場合がある。",
        "notices": "講義で紹介するフリーウェアを各自で使う場合があるため、ノートパソコンを持参すること。",
        "preparatoryStudy": "講義で取り上げる論文、受講生が発表する論文、配布物については事前に各自で読んでおくこと。",
        "gradingGuidelines": "輪講での発表と質疑応答を50点、課題レポートを50点として、100点満点で評価する。合格は60点とする。",
        "textbook": "適宜講義資料を配布する。",
        "referenceMaterials": "",
        "courseSchedule": "第1回：ガイダンス・音声・聴覚の概要（音響音声学、生成、音声知覚、聴覚モデル）第2回：音声認識１（認識・学習アルゴリズム）第3回：音声認識２（言語モデル、耐雑音処理）、その他の認識技術（話者認識、感情認識）第4回：音声合成・声質変換（音声合成、声質、韻律）第5回：音声インターフェース（対話音声、音声対話システム）第6回：さまざまな音声インターフェース第7回：まとめ",
        "courseDataUpdatedAt": "2020\/02\/20"
    },
    "updateAt": "2020\/02\/20"
}